tor_runner/__init__.py
tor_runner/__main__.py
tor_runner/common.py
tor_runner/tor_proxy.py
tor_runner/tor_runner.py
tor_runner/libraries/socks.py
tor_runner/libraries/win_inet_pton.py
tor_runner/libraries/vanguards/__init__.py
tor_runner/libraries/vanguards/bandguards.py
tor_runner/libraries/vanguards/control.py
tor_runner/libraries/vanguards/logger.py
tor_runner/libraries/vanguards/nodeselection.py
tor_runner/libraries/vanguards/pathverify.py
tor_runner/libraries/vanguards/rendguard.py
tor_runner/libraries/vanguards/vanguards.py
tor_runner-1.5.dist-info/LICENSE
tor_runner-1.5.dist-info/METADATA
tor_runner-1.5.dist-info/WHEEL
tor_runner-1.5.dist-info/entry_points.txt
tor_runner-1.5.dist-info/top_level.txt
tor_runner-1.5.dist-info/RECORD
