Metadata-Version: 2.1
Name: tor_runner
Version: 1.5
Summary: TorRunner is designed to facilitate the deployment of Tor hidden services.
Home-page: https://github.com/tn3w/TorRunner
Author: TN3W
Author-email: tn3w@protonmail.com
License: GPL-3.0
Keywords: tor,flask,sanic,hidden-service,security,privacy
Classifier: Programming Language :: Python :: 3
Classifier: License :: OSI Approved :: GNU General Public License v3 (GPLv3)
Classifier: Operating System :: OS Independent
Classifier: Development Status :: 5 - Production/Stable
Classifier: Intended Audience :: Developers
Classifier: Topic :: Internet :: Proxy Servers
Classifier: Topic :: Security :: Cryptography
Classifier: Topic :: Software Development :: Libraries :: Python Modules
Classifier: Topic :: Internet :: WWW/HTTP :: Dynamic Content
Classifier: Topic :: Internet :: WWW/HTTP :: WSGI :: Application
Classifier: Topic :: Internet :: WWW/HTTP :: WSGI :: Server
Classifier: Topic :: Internet :: WWW/HTTP :: HTTP Servers
Classifier: Topic :: Security
Classifier: Topic :: Software Development :: Libraries
Classifier: Topic :: Software Development :: Libraries :: Application Frameworks
Classifier: Topic :: System :: Networking
Classifier: Topic :: System :: Systems Administration :: Authentication/Directory
Requires-Python: >=3.6
License-File: LICENSE
